cualgo.cp312-win_amd64.pyd
cualgo-0.2.0.dist-info/LICENSE
cualgo-0.2.0.dist-info/METADATA
cualgo-0.2.0.dist-info/WHEEL
cualgo-0.2.0.dist-info/top_level.txt
cualgo-0.2.0.dist-info/RECORD
