Metadata-Version: 2.1
Name: cualgo
Version: 0.2.0
Summary: A Pytnon library containing basic algorithm with GPU-accelerated computing.
Home-page: https://github.com/anderson101866/cualgo
Download-URL: https://github.com/anderson101866/cualgo/archive/refs/tags/v0.2.0.tar.gz
Author: Anderson Meng
Author-email: andersonchi1018@gmail.com
License: MIT
Keywords: python,cuda,gpu,algorithm,numpy
Classifier: Development Status :: 4 - Beta
Classifier: Intended Audience :: Developers
Classifier: Intended Audience :: Education
Classifier: Intended Audience :: Science/Research
Classifier: Topic :: Software Development :: Libraries
Classifier: Topic :: Software Development :: Libraries :: Python Modules
Classifier: Topic :: Software Development :: Libraries
Classifier: License :: OSI Approved :: MIT License
Classifier: Programming Language :: Python :: 3
Classifier: Programming Language :: Python :: 3 :: Only
Classifier: Programming Language :: Python :: 3.7
Classifier: Programming Language :: Python :: 3.8
Classifier: Programming Language :: Python :: 3.9
Classifier: Programming Language :: Python :: 3.10
Classifier: Programming Language :: Python :: 3.11
Classifier: Programming Language :: Python :: 3.12
Classifier: Programming Language :: Python :: Implementation :: CPython
Classifier: Programming Language :: C++
Classifier: Environment :: GPU :: NVIDIA CUDA
Requires-Python: >=3.7
License-File: LICENSE
Provides-Extra: test
Requires-Dist: pytest (>=7.2) ; extra == 'test'
Requires-Dist: numpy ; extra == 'test'
